{"lastUsed":1617877102550,"path":"C:\/WorkSpace\/fore_work","projectCount":1,"recentFiles":[{"path":"\/for_work\/WebContent\/views","parentWorkspace":"C:\/WorkSpace\/fore_work","name":"icons.html","lastModified":1617864797360,"locationURI":"file:\/C:\/WorkSpace\/fore_work\/forwork\/for_work\/WebContent\/views\/icons.html"},{"path":"\/for_work\/WebContent\/views","parentWorkspace":"C:\/WorkSpace\/fore_work","name":"dashboard.html","lastModified":1617863998043,"locationURI":"file:\/C:\/WorkSpace\/fore_work\/forwork\/for_work\/WebContent\/views\/dashboard.html"},{"path":"\/for_work\/WebContent\/views","parentWorkspace":"C:\/WorkSpace\/fore_work","name":"Member.html","lastModified":1617850322352,"locationURI":"file:\/C:\/WorkSpace\/fore_work\/forwork\/for_work\/WebContent\/views\/Member.html"},{"path":"\/for_work\/WebContent\/views","parentWorkspace":"C:\/WorkSpace\/fore_work","name":"sidebar.html","lastModified":1617876004276,"locationURI":"file:\/C:\/WorkSpace\/fore_work\/forwork\/for_work\/WebContent\/views\/sidebar.html"},{"path":"\/for_work\/WebContent\/views","parentWorkspace":"C:\/WorkSpace\/fore_work","name":"NewFile.html","lastModified":1617877102817,"locationURI":"file:\/C:\/WorkSpace\/fore_work\/forwork\/for_work\/WebContent\/views\/NewFile.html"}]}